knows/__init__.py
knows/base.py
knows/nose_plugin.py
knows/pytest_plugin.py
nose_knows-0.2.dist-info/DESCRIPTION.rst
nose_knows-0.2.dist-info/METADATA
nose_knows-0.2.dist-info/RECORD
nose_knows-0.2.dist-info/WHEEL
nose_knows-0.2.dist-info/entry_points.txt
nose_knows-0.2.dist-info/metadata.json
nose_knows-0.2.dist-info/top_level.txt
nose_knows-0.2.dist-info/zip-safe
