Metadata-Version: 2.0
Name: nose-knows
Version: 0.2
Summary: UNKNOWN
Home-page: https://github.com/eventbrite/nose-knows
Author: UNKNOWN
Author-email: UNKNOWN
License: BSD
Platform: UNKNOWN
Classifier: License :: OSI Approved :: BSD License
Classifier: Programming Language :: Python :: 2.6
Classifier: Programming Language :: Python :: 2.7
